<an:akomaNtoso xmlns:an="http://docs.oasis-open.org/legaldocml/ns/akn/3.0" xmlns:gw="http://gawati.org/ns/1.0" xmlns:gxsl="http://gawati.org/ns/1.0/xsl"><an:act name="act"><an:meta><an:identification source="#gawati"><an:FRBRWork><an:FRBRthis value="/akn/tg/act/1964-12-01/arrêté_no_4-msp_du_16-64/!main"/><an:FRBRuri value="/akn/tg/act/1964-12-01/arrêté_no_4-msp_du_16-64"/><an:FRBRdate name="Work Date" date="1964-12-01"/><an:FRBRauthor href="#author"/><an:FRBRcountry value="tg" showAs="Togo"/><an:FRBRnumber value="arrêté_no_4-msp_du_16-64" showAs="Arrêté no 4-MSP du 16-64"/><an:FRBRprescriptive value="false"/><an:FRBRauthoritative value="false"/></an:FRBRWork><an:FRBRExpression><an:FRBRthis value="/akn/tg/act/1964-12-01/arrêté_no_4-msp_du_16-64/fra@/!main"/><an:FRBRuri value="/akn/tg/act/1964-12-01/arrêté_no_4-msp_du_16-64/fre@"/><an:FRBRdate name="Expression Date" date="1964-12-01"/><an:FRBRauthor href="#author"/><an:FRBRlanguage language="fra"/></an:FRBRExpression><an:FRBRManifestation><an:FRBRthis value="/akn/tg/act/1964-12-01/arrêté_no_4-msp_du_16-64/fra@/!main.xml"/><an:FRBRuri value="/akn/tg/act/1964-12-01/arrêté_no_4-msp_du_16-64/fra@/.akn"/><an:FRBRdate name="Manifestation Date" date="2016-06-02"/><an:FRBRauthor href="#author"/><an:FRBRformat value="xml"/></an:FRBRManifestation></an:identification><an:publication date="1964-12-01" showAs="Arrêté no 4-MSP du 16-64 fixant les modalités de l'examen pour l'obtention du diplôme d'Etat d'infirmiers du Togo" name="Act" number="Arrêté no 4-MSP du 16-64"/><an:classification source="#legacy"><an:keyword eId="ontology.dictionary.gawati.legacy.Examen" value="Examen" showAs="Examen" dictionary="#gawati-legacy"/><an:keyword eId="ontology.dictionary.gawati.legacy.ObtentionDuDiplôme" value="ObtentionDuDiplôme" showAs="Obtention du diplôme" dictionary="#gawati-legacy"/><an:keyword eId="ontology.dictionary.gawati.legacy.EcoleNationale" value="EcoleNationale" showAs="Ecole nationale" dictionary="#gawati-legacy"/><an:keyword eId="ontology.dictionary.gawati.legacy.EpreuvesÉcrites" value="EpreuvesÉcrites" showAs="Epreuves écrites" dictionary="#gawati-legacy"/><an:keyword eId="ontology.dictionary.gawati.legacy.EducationSanitaire" value="EducationSanitaire" showAs="Education sanitaire" dictionary="#gawati-legacy"/><an:keyword eId="ontology.dictionary.gawati.legacy.Candidats" value="Candidats" showAs="Candidats" dictionary="#gawati-legacy"/><an:keyword eId="ontology.dictionary.gawati.legacy.EpreuvesOrales" value="EpreuvesOrales" showAs="Epreuves orales" dictionary="#gawati-legacy"/></an:classification><an:lifecycle source="#all"><an:eventRef date="1964-12-01" source="#original" type="generation"/><an:eventRef date="1964-12-01" source="#original" type="generatio" refersTo="#dtInForce"/></an:lifecycle><an:references source="#source"><an:original eId="original" href="/akn/tg/act/1964-12-01/arrêté_no_4-msp_du_16-64/fra@/!main" showAs="Arrêté no 4-MSP du 16-64"/><an:TLCOrganization eId="all" href="/ontology/Organization/AfricanLawLibrary" showAs="African Law Library"/><an:TLCEvent eId="dtInForce" href="/ontology/Event/ALL/InForce" showAs="Entry into Force Date"/><an:TLCConcept eId="ct-Legal-PublicServices" href="/ontology/Concept/Legacy/Legal/PublicServices" showAs="Public Services"/><an:TLCConcept eId="ct-Legal-Education" href="/ontology/Concept/Legacy/Legal/Education" showAs="Education"/></an:references><an:proprietary source="#all"><gw:gawati><gw:legacyIdentifier>africanlawlib:6712341</gw:legacyIdentifier><gw:legacyOwner>17066796</gw:legacyOwner><gw:legacyCollection>L03050 Togo</gw:legacyCollection><gw:languages><gw:language code="fre"/></gw:languages><gw:embeddedContents><gw:embeddedContent eId="embedded-doc-1" type="pdf" file="TGMJ_jo_1964-270-2y.pdf" state="true"/></gw:embeddedContents><gw:dateTime refersTo="#dtCreated" datetime="2016-02-10T08:54:41.630Z"/><gw:dateTime refersTo="#dtModified" datetime="2016-06-02T08:28:32.496Z"/><gw:date refersTo="#dtInForce" date="1964-12-01"/><gw:date refersTo="#dtEnactmentDate" date="1964-11-16"/><gw:themes source="#legacy"><gw:theme refersTo="#ct-Legal-PublicServices"/><gw:theme refersTo="#ct-Legal-Education"/></gw:themes></gw:gawati></an:proprietary></an:meta><an:body><an:book refersTo="#mainDocument"><an:componentRef src="/akn/tg/act/1964-12-01/arrêté_no_4-msp_du_16-64/fra@/!main.pdf" alt="akn_tg_act_1964-12-01_arrêté_no_4-msp_du_16-64_fra_main.pdf" GUID="#embedded-doc-1" showAs="Arrêté no 4-MSP du 16-64 fixant les modalités de l'examen pour l'obtention du diplôme d'Etat d'infirmiers du Togo"/></an:book></an:body></an:act></an:akomaNtoso>