<an:akomaNtoso xmlns:an="http://docs.oasis-open.org/legaldocml/ns/akn/3.0" xmlns:gw="http://gawati.org/ns/1.0" xmlns:gxsl="http://gawati.org/ns/1.0/xsl"><an:act name="act"><an:meta><an:identification source="#gawati"><an:FRBRWork><an:FRBRthis value="/akn/bj/act/2001-02-20/decret_no2001-095/!main"/><an:FRBRuri value="/akn/bj/act/2001-02-20/decret_no2001-095"/><an:FRBRdate name="Work Date" date="2001-02-20"/><an:FRBRauthor href="#author"/><an:FRBRcountry value="bj" showAs="Benin"/><an:FRBRnumber value="decret_no2001-095" showAs="DECRET NO.2001-095"/><an:FRBRprescriptive value="false"/><an:FRBRauthoritative value="false"/></an:FRBRWork><an:FRBRExpression><an:FRBRthis value="/akn/bj/act/2001-02-20/decret_no2001-095/fra@/!main"/><an:FRBRuri value="/akn/bj/act/2001-02-20/decret_no2001-095/fre@"/><an:FRBRdate name="Expression Date" date="2001-02-20"/><an:FRBRauthor href="#author"/><an:FRBRlanguage language="fra"/></an:FRBRExpression><an:FRBRManifestation><an:FRBRthis value="/akn/bj/act/2001-02-20/decret_no2001-095/fra@/!main.xml"/><an:FRBRuri value="/akn/bj/act/2001-02-20/decret_no2001-095/fra@/.akn"/><an:FRBRdate name="Manifestation Date" date="2015-06-04"/><an:FRBRauthor href="#author"/><an:FRBRformat value="xml"/></an:FRBRManifestation></an:identification><an:publication date="2001-02-20" showAs="DECRET NO.2001-095 DU 20 FEVRIER 2001 PORTANT CREATION, ATTRIBUTIONS,ORGANISATION ET FONCTIONNEMENT DES CELLULES ENVIRONNEMENTALES EN REPUBLIQUE DU BENIN." name="Act" number="DECRET NO.2001-095"/><an:classification source="#legacy"><an:keyword eId="ontology.dictionary.gawati.legacy.Prefecture" value="Prefecture" showAs="Prefecture" dictionary="#gawati-legacy"/><an:keyword eId="ontology.dictionary.gawati.legacy.Environnement" value="Environnement" showAs="Environnement" dictionary="#gawati-legacy"/><an:keyword eId="ontology.dictionary.gawati.legacy.Programmes" value="Programmes" showAs="Programmes" dictionary="#gawati-legacy"/><an:keyword eId="ontology.dictionary.gawati.legacy.ProjetsDeDeveloppement" value="ProjetsDeDeveloppement" showAs="Projets de developpement" dictionary="#gawati-legacy"/><an:keyword eId="ontology.dictionary.gawati.legacy.Interface" value="Interface" showAs="Interface" dictionary="#gawati-legacy"/><an:keyword eId="ontology.dictionary.gawati.legacy.UniteFonctionnelle" value="UniteFonctionnelle" showAs="Unite fonctionnelle" dictionary="#gawati-legacy"/><an:keyword eId="ontology.dictionary.gawati.legacy.Integration" value="Integration" showAs="Integration" dictionary="#gawati-legacy"/><an:keyword eId="ontology.dictionary.gawati.legacy.Programmation" value="Programmation" showAs="Programmation" dictionary="#gawati-legacy"/></an:classification><an:lifecycle source="#all"><an:eventRef date="2001-02-20" source="#original" type="generation"/><an:eventRef date="2001-02-20" source="#original" type="generatio" refersTo="#dtInForce"/></an:lifecycle><an:references source="#source"><an:original eId="original" href="/akn/bj/act/2001-02-20/decret_no2001-095/fra@/!main" showAs="DECRET NO.2001-095"/><an:TLCOrganization eId="all" href="/ontology/Organization/AfricanLawLibrary" showAs="African Law Library"/><an:TLCEvent eId="dtInForce" href="/ontology/Event/ALL/InForce" showAs="Entry into Force Date"/><an:TLCConcept eId="ct-Legal-Environment" href="/ontology/Concept/Legacy/Legal/Environment" showAs="Environment"/></an:references><an:proprietary source="#all"><gw:gawati><gw:legacyIdentifier>africanlawlib:6600308</gw:legacyIdentifier><gw:legacyOwner>16382168</gw:legacyOwner><gw:legacyCollection>L03003</gw:legacyCollection><gw:languages><gw:language code="fre"/></gw:languages><gw:embeddedContents><gw:embeddedContent eId="embedded-doc-1" type="pdf" file="doc632.pdf" state="true"/></gw:embeddedContents><gw:dateTime refersTo="#dtCreated" datetime="2015-04-30T12:03:11.420Z"/><gw:dateTime refersTo="#dtModified" datetime="2015-06-04T09:29:34.044Z"/><gw:date refersTo="#dtInForce" date="2001-02-20"/><gw:themes source="#legacy"><gw:theme refersTo="#ct-Legal-Environment"/></gw:themes></gw:gawati></an:proprietary></an:meta><an:body><an:book refersTo="#mainDocument"><an:componentRef src="/akn/bj/act/2001-02-20/decret_no2001-095/fra@/!main.pdf" alt="akn_bj_act_2001-02-20_decret_no2001-095_fra_main.pdf" GUID="#embedded-doc-1" showAs="DECRET NO.2001-095 DU 20 FEVRIER 2001 PORTANT CREATION, ATTRIBUTIONS,ORGANISATION ET FONCTIONNEMENT DES CELLULES ENVIRONNEMENTALES EN REPUBLIQUE DU BENIN."/></an:book></an:body></an:act></an:akomaNtoso>