<an:akomaNtoso xmlns:an="http://docs.oasis-open.org/legaldocml/ns/akn/3.0" xmlns:gw="http://gawati.org/ns/1.0" xmlns:gxsl="http://gawati.org/ns/1.0/xsl"><an:act name="act"><an:meta><an:identification source="#gawati"><an:FRBRWork><an:FRBRthis value="/akn/tg/act/1997-01-12/loi_no_97-02/!main"/><an:FRBRuri value="/akn/tg/act/1997-01-12/loi_no_97-02"/><an:FRBRdate name="Work Date" date="1997-01-12"/><an:FRBRauthor href="#author"/><an:FRBRcountry value="tg" showAs="Togo"/><an:FRBRnumber value="loi_no_97-02" showAs="Loi No 97-02"/><an:FRBRprescriptive value="false"/><an:FRBRauthoritative value="false"/></an:FRBRWork><an:FRBRExpression><an:FRBRthis value="/akn/tg/act/1997-01-12/loi_no_97-02/fra@/!main"/><an:FRBRuri value="/akn/tg/act/1997-01-12/loi_no_97-02/fre@"/><an:FRBRdate name="Expression Date" date="1997-01-12"/><an:FRBRauthor href="#author"/><an:FRBRlanguage language="fra"/></an:FRBRExpression><an:FRBRManifestation><an:FRBRthis value="/akn/tg/act/1997-01-12/loi_no_97-02/fra@/!main.xml"/><an:FRBRuri value="/akn/tg/act/1997-01-12/loi_no_97-02/fra@/.akn"/><an:FRBRdate name="Manifestation Date" date="2016-03-29"/><an:FRBRauthor href="#author"/><an:FRBRformat value="xml"/></an:FRBRManifestation></an:identification><an:publication date="1997-01-12" showAs="Loi No 97-02 du 10 janvier 1997 portant création d'un fonds d'entretien routier (FER)" name="Act" number="Loi No 97-02"/><an:classification source="#legacy"><an:keyword eId="ontology.dictionary.gawati.legacy.Établissement" value="Établissement" showAs="Établissement" dictionary="#gawati-legacy"/><an:keyword eId="ontology.dictionary.gawati.legacy.Commerce" value="Commerce" showAs="Commerce" dictionary="#gawati-legacy"/><an:keyword eId="ontology.dictionary.gawati.legacy.Transporteurs" value="Transporteurs" showAs="Transporteurs" dictionary="#gawati-legacy"/><an:keyword eId="ontology.dictionary.gawati.legacy.Fonds" value="Fonds" showAs="Fonds" dictionary="#gawati-legacy"/><an:keyword eId="ontology.dictionary.gawati.legacy.Financement" value="Financement" showAs="Financement" dictionary="#gawati-legacy"/><an:keyword eId="ontology.dictionary.gawati.legacy.Travaux" value="Travaux" showAs="Travaux" dictionary="#gawati-legacy"/><an:keyword eId="ontology.dictionary.gawati.legacy.Pistes" value="Pistes" showAs="Pistes" dictionary="#gawati-legacy"/><an:keyword eId="ontology.dictionary.gawati.legacy.Route" value="Route" showAs="Route" dictionary="#gawati-legacy"/><an:keyword eId="ontology.dictionary.gawati.legacy.Budget" value="Budget" showAs="Budget" dictionary="#gawati-legacy"/><an:keyword eId="ontology.dictionary.gawati.legacy.Fonctionnement" value="Fonctionnement" showAs="Fonctionnement" dictionary="#gawati-legacy"/></an:classification><an:lifecycle source="#all"><an:eventRef date="1997-01-12" source="#original" type="generation"/><an:eventRef date="1997-01-12" source="#original" type="generatio" refersTo="#dtInForce"/></an:lifecycle><an:references source="#source"><an:original eId="original" href="/akn/tg/act/1997-01-12/loi_no_97-02/fra@/!main" showAs="Loi No 97-02"/><an:TLCOrganization eId="all" href="/ontology/Organization/AfricanLawLibrary" showAs="African Law Library"/><an:TLCEvent eId="dtInForce" href="/ontology/Event/ALL/InForce" showAs="Entry into Force Date"/><an:TLCConcept eId="ct-Legal-Finance" href="/ontology/Concept/Legacy/Legal/Finance" showAs="Finance"/><an:TLCConcept eId="ct-Legal-BankingLaw" href="/ontology/Concept/Legacy/Legal/BankingLaw" showAs="Banking Law"/><an:TLCConcept eId="ct-Legal-PublicServices" href="/ontology/Concept/Legacy/Legal/PublicServices" showAs="Public Services"/><an:TLCConcept eId="ct-Legal-Transport" href="/ontology/Concept/Legacy/Legal/Transport" showAs="Transport"/></an:references><an:proprietary source="#all"><gw:gawati><gw:legacyIdentifier>africanlawlib:6739392</gw:legacyIdentifier><gw:legacyOwner>17474215</gw:legacyOwner><gw:legacyCollection>L03050 Togo</gw:legacyCollection><gw:languages><gw:language code="fre"/></gw:languages><gw:embeddedContents><gw:embeddedContent eId="embedded-doc-1" type="pdf" file="TGMJ_jo_1997-003.pdf" state="true"/></gw:embeddedContents><gw:dateTime refersTo="#dtCreated" datetime="2016-03-16T06:00:58.591Z"/><gw:dateTime refersTo="#dtModified" datetime="2016-03-29T07:21:45.287Z"/><gw:date refersTo="#dtInForce" date="1997-01-12"/><gw:date refersTo="#dtEnactmentDate" date="1997-01-10"/><gw:themes source="#legacy"><gw:theme refersTo="#ct-Legal-Finance"/><gw:theme refersTo="#ct-Legal-BankingLaw"/><gw:theme refersTo="#ct-Legal-PublicServices"/><gw:theme refersTo="#ct-Legal-Transport"/></gw:themes></gw:gawati></an:proprietary></an:meta><an:body><an:book refersTo="#mainDocument"><an:componentRef src="/akn/tg/act/1997-01-12/loi_no_97-02/fra@/!main.pdf" alt="akn_tg_act_1997-01-12_loi_no_97-02_fra_main.pdf" GUID="#embedded-doc-1" showAs="Loi No 97-02 du 10 janvier 1997 portant création d'un fonds d'entretien routier (FER)"/></an:book></an:body></an:act></an:akomaNtoso>